shelfie/__init__.py
shelfie/data.py
shelfie/fields.py
shelfie/shelf.py
shelfie-0.2.0.dist-info/METADATA
shelfie-0.2.0.dist-info/WHEEL
shelfie-0.2.0.dist-info/licenses/LICENSE
shelfie-0.2.0.dist-info/RECORD
