Metadata-Version: 2.4
Name: shelfie
Version: 0.2.0
Summary: Filesystem-based structured storage for data with metadata - the middle ground between scattered files and databases
Project-URL: Homepage, https://github.com/maxrdu/shelfie
Project-URL: Repository, https://github.com/maxrdu/shelfie
Project-URL: Documentation, https://github.com/maxrdu/shelfie#readme
Project-URL: Bug Tracker, https://github.com/maxrdu/shelfie/issues
Author-email: Max Rausch-Dupont <max@rausch-dupont.de>
License-File: LICENSE
Keywords: data,experiments,filesystem,metadata,ml,organization,storage
Classifier: Development Status :: 3 - Alpha
Classifier: Intended Audience :: Developers
Classifier: Intended Audience :: Science/Research
Classifier: License :: OSI Approved :: MIT License
Classifier: Programming Language :: Python :: 3
Classifier: Programming Language :: Python :: 3.10
Classifier: Programming Language :: Python :: 3.11
Classifier: Programming Language :: Python :: 3.12
Classifier: Topic :: Database
Classifier: Topic :: Scientific/Engineering
Classifier: Topic :: System :: Filesystems
Requires-Python: >=3.10
Requires-Dist: numpy>=2.2.6
Requires-Dist: pandas>=2.3.0
